tokengen/__init__.py
tokengen/cli.py
tokengen/source.py
tokengen-0.1.1.dist-info/LICENSE
tokengen-0.1.1.dist-info/METADATA
tokengen-0.1.1.dist-info/WHEEL
tokengen-0.1.1.dist-info/entry_points.txt
tokengen-0.1.1.dist-info/top_level.txt
tokengen-0.1.1.dist-info/RECORD
