Metadata-Version: 2.1
Name: tokengen
Version: 0.1.1
Summary: A simple CLI utility for automating token generations with kubernetes.
Home-page: 
Author: Sharhan Alhassan
Author-email: sharhan.alhassan@tiacloud.co
Classifier: Programming Language :: Python :: 3.9
Classifier: License :: OSI Approved :: MIT License
Requires-Python: >=3.9
License-File: LICENSE
Requires-Dist: azure-common (==1.1.28)
Requires-Dist: azure-core (==1.26.1)
Requires-Dist: azure-identity (==1.12.0)
Requires-Dist: azure-keyvault-secrets (==4.6.0)
Requires-Dist: certifi (==2022.9.24)
Requires-Dist: cffi (==1.15.1)
Requires-Dist: charset-normalizer (==2.1.1)
Requires-Dist: cryptography (==38.0.4)
Requires-Dist: docker (==6.0.1)
Requires-Dist: fire (==0.4.0)
Requires-Dist: idna (==3.4)
Requires-Dist: isodate (==0.6.1)
Requires-Dist: msal (==1.20.0)
Requires-Dist: msal-extensions (==1.0.0)
Requires-Dist: msrest (==0.7.1)
Requires-Dist: oauthlib (==3.2.2)
Requires-Dist: packaging (==21.3)
Requires-Dist: portalocker (==2.6.0)
Requires-Dist: pycparser (==2.21)
Requires-Dist: PyJWT (==2.6.0)
Requires-Dist: pyparsing (==3.0.9)
Requires-Dist: randomname (==0.1.5)
Requires-Dist: requests (==2.28.1)
Requires-Dist: requests-oauthlib (==1.3.1)
Requires-Dist: six (==1.16.0)
Requires-Dist: termcolor (==2.1.1)
Requires-Dist: typing-extensions (==4.4.0)
Requires-Dist: urllib3 (==1.26.13)
Requires-Dist: websocket-client (==1.4.2)
